sql_debug/__init__.py
sql_debug/apps.py
sql_debug/middleware.py
sql_debug/models.py
sql_debug/settings.py
sql_debug/urls.py
sql_debug/views.py
sql_debug/migrations/0001_initial.py
sql_debug/migrations/__init__.py
sql_debug/static/sql_debug/default.css
sql_debug/static/sql_debug/highlight.pack.js
sql_debug/templates/sql_debug/sql_debug_detail.html
sql_debug/templates/sql_debug/sql_debug_list.html
django_simple_sql_debug-0.2.1.dist-info/AUTHORS.rst
django_simple_sql_debug-0.2.1.dist-info/LICENSE
django_simple_sql_debug-0.2.1.dist-info/METADATA
django_simple_sql_debug-0.2.1.dist-info/WHEEL
django_simple_sql_debug-0.2.1.dist-info/top_level.txt
django_simple_sql_debug-0.2.1.dist-info/RECORD
