Metadata-Version: 2.1
Name: django-simple-sql-debug
Version: 0.2.1
Summary: Your project description goes here
Home-page: https://github.com/pylame22/django-simple-sql-debug
Author: Albert
Author-email: pylame22@yandex.ru
License: BSD
Keywords: django-simple-sql-debug
Platform: UNKNOWN
Classifier: Development Status :: 3 - Alpha
Classifier: Framework :: Django :: 1.11
Classifier: Framework :: Django :: 2.0
Classifier: Intended Audience :: Developers
Classifier: License :: OSI Approved :: BSD License
Classifier: Natural Language :: English
Classifier: Programming Language :: Python :: 2
Classifier: Programming Language :: Python :: 2.7
Classifier: Programming Language :: Python :: 3
Classifier: Programming Language :: Python :: 3.4
Classifier: Programming Language :: Python :: 3.5
Classifier: Programming Language :: Python :: 3.6
